bigfeat.py
django_bigfeat-0.1.1.dist-info/DESCRIPTION.rst
django_bigfeat-0.1.1.dist-info/METADATA
django_bigfeat-0.1.1.dist-info/RECORD
django_bigfeat-0.1.1.dist-info/WHEEL
django_bigfeat-0.1.1.dist-info/metadata.json
django_bigfeat-0.1.1.dist-info/top_level.txt
