Metadata-Version: 2.0
Name: django-bigfeat
Version: 0.1.1
Summary: Custom field to add multiple boolean features using a BigIntegerField.
Home-page: https://github.com/f0r4y312/django-bigfeat
Author: Vimal Aravindashan
Author-email: vimal.aravindashan@gmail.com
License: MIT
Platform: any
Classifier: Environment :: Web Environment
Classifier: Framework :: Django
Classifier: Framework :: Django :: 1.8
Classifier: Intended Audience :: Developers
Classifier: License :: OSI Approved :: MIT License
Classifier: Operating System :: OS Independent
Classifier: Programming Language :: Python
Classifier: Programming Language :: Python :: 2
Classifier: Programming Language :: Python :: 2.7
Classifier: Topic :: Internet :: WWW/HTTP
Classifier: Topic :: Internet :: WWW/HTTP :: Dynamic Content
Requires-Dist: django (>=1.8,<2)
